{
  "version": "7",
  "dialect": "postgresql",
  "entries": [
    {
      "idx": 0,
      "version": "7",
      "when": 1778316507981,
      "tag": "0000_thin_matthew_murdock",
      "breakpoints": true
    },
    {
      "idx": 1,
      "version": "7",
      "when": 1778407523562,
      "tag": "0001_phase3_intake",
      "breakpoints": true
    },
    {
      "idx": 2,
      "version": "7",
      "when": 1747094400000,
      "tag": "0002_phase3_multi_service",
      "breakpoints": true
    }
  ]
}